bexio_api_python_client-0.1.5.dist-info/DESCRIPTION.rst
bexio_api_python_client-0.1.5.dist-info/METADATA
bexio_api_python_client-0.1.5.dist-info/RECORD
bexio_api_python_client-0.1.5.dist-info/WHEEL
bexio_api_python_client-0.1.5.dist-info/metadata.json
bexio_api_python_client-0.1.5.dist-info/top_level.txt
bexiopy/__init__.py
bexiopy/admin.py
bexiopy/api.py
bexiopy/apps.py
bexiopy/helpers.py
bexiopy/models.py
bexiopy/settings.py
bexiopy/urls.py
bexiopy/views.py
bexiopy/migrations/__init__.py
bexiopy/resources/__init__.py
bexiopy/resources/base.py
bexiopy/resources/contacts.py
bexiopy/resources/general.py
bexiopy/resources/invoices.py
bexiopy/static/css/bexiopy.css
bexiopy/static/js/bexiopy.js
bexiopy/templates/bexiopy/base.html
