Metadata-Version: 2.0
Name: bexio-api-python-client
Version: 0.1.5
Summary: Bexio API Python Client
Home-page: https://github.com/oesah/bexio-api-python-client
Author: Özer Sahin
Author-email: o.sahin@oesah.de
License: MIT
Keywords: bexio-api-python-client
Platform: UNKNOWN
Classifier: Development Status :: 3 - Alpha
Classifier: Framework :: Django
Classifier: Framework :: Django :: 1.8
Classifier: Framework :: Django :: 1.9
Classifier: Framework :: Django :: 1.10
Classifier: Intended Audience :: Developers
Classifier: License :: OSI Approved :: BSD License
Classifier: Natural Language :: English
Classifier: Programming Language :: Python :: 2
Classifier: Programming Language :: Python :: 2.7
Classifier: Programming Language :: Python :: 3
Classifier: Programming Language :: Python :: 3.3
Classifier: Programming Language :: Python :: 3.4
Classifier: Programming Language :: Python :: 3.5
